mx8fs/__init__.py
mx8fs/cache.py
mx8fs/comparer.py
mx8fs/file_io.py
mx8fs/lock.py
mx8fs/storage.py
mx8fs-1.1.0.27.dist-info/METADATA
mx8fs-1.1.0.27.dist-info/WHEEL
mx8fs-1.1.0.27.dist-info/RECORD
