Metadata-Version: 2.4
Name: mx8fs
Version: 1.1.0.27
Summary: MX8 Filing system
License: MIT
Author: Tom Weiss
Author-email: tom@mx8labs.com
Requires-Python: >=3.12
Classifier: License :: OSI Approved :: MIT License
Classifier: Programming Language :: Python :: 3
Classifier: Programming Language :: Python :: 3.12
Classifier: Programming Language :: Python :: 3.13
Classifier: Programming Language :: Python :: 3.14
Requires-Dist: boto3 (>=1.26.137)
